{
  "$schema": "https://mintlify.com/docs.json",
  "theme": "mint",
  "name": "Porttera Bundles",
  "description": "Install, configure, customize, and uninstall Porttera Bundles.",
  "colors": {
    "primary": "#111111",
    "light": "#f9f9f5",
    "dark": "#111111"
  },
  "appearance": {
    "default": "dark"
  },
  "fonts": {
    "family": "Inter"
  },
  "background": {
    "color": {
      "light": "#f9f9f5",
      "dark": "#111111"
    }
  },
  "styling": {
    "codeblocks": "dark"
  },
  "favicon": "/favicon.svg",
  "logo": {
    "light": "/logo/light.svg",
    "dark": "/logo/dark.svg"
  },
  "navigation": {
    "groups": [
      { "group": "Welcome", "pages": ["index", "faq", "changelog"] },
      {
        "group": "Bundles",
        "pages": [
          "bundles/overview",
          "bundles/installation",
          "bundles/configuration",
          "bundles/customization",
          "bundles/features",
          "bundles/how-it-works",
          "bundles/uninstalling",
          "bundles/troubleshooting"
        ]
      }
    ]
  },
  "navbar": {
    "links": [
      { "label": "Support", "href": "https://porttera.com/pages/contact" }
    ],
    "primary": { "type": "button", "label": "porttera.com", "href": "https://porttera.com" }
  },
  "footer": {
    "socials": { "website": "https://porttera.com" }
  }
}
